async_http_client/__init__.py
async_http_client-1.0.0.dist-info/LICENSE
async_http_client-1.0.0.dist-info/METADATA
async_http_client-1.0.0.dist-info/WHEEL
async_http_client-1.0.0.dist-info/top_level.txt
async_http_client-1.0.0.dist-info/RECORD
