Metadata-Version: 2.1
Name: async-http-client
Version: 1.0.0
Summary: Async HTTP Client
Home-page: UNKNOWN
Author: jaytarang92
Author-email: jaytarang92@gmail.com
License: UNKNOWN
Platform: UNKNOWN
Classifier: Programming Language :: Python :: 3.5
Classifier: Programming Language :: Python :: 3.6
Classifier: Programming Language :: Python :: 3.7
Classifier: Programming Language :: Python :: 3.8
Requires-Python: >=3.5
Requires-Dist: aiohttp (==3.6.3)
